dbgpt_acc_auto/__init__.py
dbgpt_acc_auto/_version.py
dbgpt_acc_auto-0.7.4.dist-info/METADATA
dbgpt_acc_auto-0.7.4.dist-info/WHEEL
dbgpt_acc_auto-0.7.4.dist-info/RECORD
